db_mysql.py
db_mysql-0.1.2.dist-info/LICENSE
db_mysql-0.1.2.dist-info/METADATA
db_mysql-0.1.2.dist-info/WHEEL
db_mysql-0.1.2.dist-info/top_level.txt
db_mysql-0.1.2.dist-info/RECORD
