Metadata-Version: 2.1
Name: db-mysql
Version: 0.1.2
Summary: 一个基于pymysql的操作mysql的简易框架
Home-page: https://github.com/WRAllen/db-mysql
Author: WRAllen
Author-email: 1072274105@qq.com
License: UNKNOWN
Platform: UNKNOWN
Requires-Dist: PyMySQL (>=0.10.1)
